README.txt
setup.py
docs/HISTORY.txt
mobile/__init__.py
mobile.htmlprocessing.egg-info/PKG-INFO
mobile.htmlprocessing.egg-info/SOURCES.txt
mobile.htmlprocessing.egg-info/dependency_links.txt
mobile.htmlprocessing.egg-info/entry_points.txt
mobile.htmlprocessing.egg-info/namespace_packages.txt
mobile.htmlprocessing.egg-info/not-zip-safe
mobile.htmlprocessing.egg-info/requires.txt
mobile.htmlprocessing.egg-info/top_level.txt
mobile/htmlprocessing/__init__.py
mobile/htmlprocessing/utilities.py
mobile/htmlprocessing/tests/__init__.py
mobile/htmlprocessing/tests/test_img.py
mobile/htmlprocessing/tests/test_resize.py
mobile/htmlprocessing/tests/test_unicode.py
mobile/htmlprocessing/transformers/__init__.py
mobile/htmlprocessing/transformers/basic.py
mobile/htmlprocessing/transformers/imageresizer.py