Metadata-Version: 1.0
Name: mobile.htmlprocessing
Version: 0.1
Summary: HTML processing helpers for mobile sites
Home-page: http://svn.plone.org/svn/collective/
Author: UNKNOWN
Author-email: UNKNOWN
License: GPL
Keywords: html xhtml mobile image processor
Platform: UNKNOWN
Classifier: Programming Language :: Python
